liblib_ai_mcp/__init__.py
liblib_ai_mcp/main.py
liblib_ai_mcp-1.0.0.dist-info/licenses/LICENSE
liblib_ai_mcp-1.0.0.dist-info/METADATA
liblib_ai_mcp-1.0.0.dist-info/WHEEL
liblib_ai_mcp-1.0.0.dist-info/entry_points.txt
liblib_ai_mcp-1.0.0.dist-info/top_level.txt
liblib_ai_mcp-1.0.0.dist-info/RECORD
