Metadata-Version: 2.4
Name: liblib-ai-mcp
Version: 1.0.0
Summary: LiblibAI AI图片生成MCP工具 - 支持各种风格的AI图片创作
Home-page: https://github.com/yourusername/liblib-ai-mcp
Author: LiblibAI MCP Developer
Author-email: LiblibAI MCP Developer <developer@example.com>
License: MIT
Project-URL: Homepage, https://github.com/yourusername/liblib-ai-mcp
Project-URL: Repository, https://github.com/yourusername/liblib-ai-mcp
Project-URL: Issues, https://github.com/yourusername/liblib-ai-mcp/issues
Keywords: ai,image-generation,mcp,liblib,artificial-intelligence,text-to-image
Classifier: Development Status :: 5 - Production/Stable
Classifier: Intended Audience :: Developers
Classifier: License :: OSI Approved :: MIT License
Classifier: Operating System :: OS Independent
Classifier: Programming Language :: Python :: 3
Classifier: Programming Language :: Python :: 3.8
Classifier: Programming Language :: Python :: 3.9
Classifier: Programming Language :: Python :: 3.10
Classifier: Programming Language :: Python :: 3.11
Classifier: Programming Language :: Python :: 3.12
Classifier: Topic :: Software Development :: Libraries :: Python Modules
Classifier: Topic :: Multimedia :: Graphics
Classifier: Topic :: Scientific/Engineering :: Artificial Intelligence
Requires-Python: >=3.8
License-File: LICENSE
Requires-Dist: mcp>=1.0.0
Requires-Dist: fastmcp>=0.1.0
Requires-Dist: requests>=2.25.0
Dynamic: author
Dynamic: home-page
Dynamic: license-file
Dynamic: requires-python
